altair_express/__init__.py
altair_express/actions.py
altair_express/altair_express.py
altair_express/cli.py
altair_express/distributional.py
altair_express/effects.py
altair_express/interactions.py
altair_express/jointplot.py
altair_express/pairplot.py
altair_express/profile.py
altair_express/relational.py
altair_express/utils.py
altair_express/relational/joint_plot.py
altair_express/relational/relational.py
altair_express-0.1.30.dist-info/METADATA
altair_express-0.1.30.dist-info/WHEEL
altair_express-0.1.30.dist-info/entry_points.txt
altair_express-0.1.30.dist-info/licenses/AUTHORS.rst
altair_express-0.1.30.dist-info/licenses/LICENSE
altair_express-0.1.30.dist-info/RECORD
