Metadata-Version: 2.3
Name: altair_express
Version: 0.1.30
Summary: Create interactive data visualizations in one line of code.
Project-URL: homepage, https://github.com/dwootton/altair_express
Project-URL: Source, https://github.com/dwootton/Altair-Express
Author-email: Dylan Wootton <dwootton@mit.edu>
License: MIT License
License-File: AUTHORS.rst
License-File: LICENSE
Keywords: altair_express
Classifier: Development Status :: 2 - Pre-Alpha
Classifier: Intended Audience :: Developers
Classifier: License :: OSI Approved :: MIT License
Classifier: Natural Language :: English
Classifier: Programming Language :: Python :: 3
Classifier: Programming Language :: Python :: 3.6
Classifier: Programming Language :: Python :: 3.7
Classifier: Programming Language :: Python :: 3.8
Requires-Dist: jinja2
Requires-Dist: jsonschema>=3.0
Requires-Dist: numpy
Requires-Dist: packaging
Requires-Dist: pandas>=0.25
Requires-Dist: setuptools
Requires-Dist: toolz
Requires-Dist: typing-extensions>=4.0.1; python_version < '3.11'
Provides-Extra: all
Requires-Dist: altair-alx-alpha; extra == 'all'
Requires-Dist: altair-tiles>=0.3.0; extra == 'all'
Requires-Dist: anywidget>=0.9.0; extra == 'all'
Requires-Dist: pyarrow>=11; extra == 'all'
Requires-Dist: vega-datasets>=0.9.0; extra == 'all'
Requires-Dist: vegafusion[embed]>=1.6.6; extra == 'all'
Requires-Dist: vl-convert-python>=1.3.0; extra == 'all'
Provides-Extra: dev
Requires-Dist: altair-alx-alpha>=5.4.1a0; extra == 'dev'
Requires-Dist: geopandas; extra == 'dev'
Requires-Dist: hatch; extra == 'dev'
Requires-Dist: ipython; extra == 'dev'
Requires-Dist: jupyterlab>=4.1.5; extra == 'dev'
Requires-Dist: m2r; extra == 'dev'
Requires-Dist: mypy; extra == 'dev'
Requires-Dist: pandas-stubs; extra == 'dev'
Requires-Dist: pytest; extra == 'dev'
Requires-Dist: pytest-cov; extra == 'dev'
Requires-Dist: ruff>=0.3.0; extra == 'dev'
Requires-Dist: types-jsonschema; extra == 'dev'
Requires-Dist: types-setuptools; extra == 'dev'
Provides-Extra: doc
Requires-Dist: altair-alx-alpha; extra == 'doc'
Requires-Dist: docutils; extra == 'doc'
Requires-Dist: jinja2; extra == 'doc'
Requires-Dist: jupyterlite-pyodide-kernel; extra == 'doc'
Requires-Dist: jupyterlite-sphinx; extra == 'doc'
Requires-Dist: myst-parser; extra == 'doc'
Requires-Dist: numpydoc; extra == 'doc'
Requires-Dist: pillow<10,>=9; extra == 'doc'
Requires-Dist: pydata-sphinx-theme>=0.14.1; extra == 'doc'
Requires-Dist: scipy; extra == 'doc'
Requires-Dist: sphinx; extra == 'doc'
Requires-Dist: sphinx-copybutton; extra == 'doc'
Requires-Dist: sphinx-design; extra == 'doc'
Requires-Dist: sphinxext-altair; extra == 'doc'
